savemoney/__about__.py
savemoney/__init__.py
savemoney/ca2bam/__init__.py
savemoney/ca2bam/__main__.py
savemoney/ca2bam/ca2bam.py
savemoney/modules/__init__.py
savemoney/modules/gen_stats.py
savemoney/modules/msa.py
savemoney/modules/my_classes.py
savemoney/modules/ref_query_alignment.py
savemoney/modules/NanoporeStats_PDF/NanoporeStats_pdf_0.2.0.csv
savemoney/modules/cython_functions/__init__.py
savemoney/modules/cython_functions/alignment_functions.cpp
savemoney/modules/cython_functions/alignment_functions.cpython-310-darwin.so
savemoney/modules/cython_functions/alignment_functions.pyx
savemoney/modules/cython_functions/alignment_functions_setup.py
savemoney/post_analysis/__init__.py
savemoney/post_analysis/__main__.py
savemoney/post_analysis/post_analysis.py
savemoney/post_analysis/post_analysis_core.py
savemoney/pre_survey/__init__.py
savemoney/pre_survey/__main__.py
savemoney/pre_survey/pre_survey.py
savemoney/pre_survey/pre_survey_core.py
savemoney/show_consensus/__init__.py
savemoney/show_consensus/__main__.py
savemoney/show_consensus/show_consensus.py
savemoney-0.3.7.dist-info/LICENSE
savemoney-0.3.7.dist-info/METADATA
savemoney-0.3.7.dist-info/WHEEL
savemoney-0.3.7.dist-info/top_level.txt
savemoney-0.3.7.dist-info/RECORD
