Metadata-Version: 2.1
Name: savemoney
Version: 0.3.7
Summary: Simple Algorithm for Very Efficient Multiplexing of Oxford Nanopore Experiments for You!
Home-page: https://github.com/MasaakiU/MultiplexNanopore
Author: Masaaki Uematsu
Author-email: mu84@cornell.edu
Maintainer: Masaaki Uematsu
Maintainer-email: mu84@cornell.edu
License: CC BY-NC-SA 4.0
Keywords: plasmid,whole-plasmid,sequencing,alignment,multiplexing,barcode-free,bayesian analysis,prior information,
Classifier: Development Status :: 4 - Beta
Classifier: License :: Free for non-commercial use
Classifier: Programming Language :: Cython
Classifier: Programming Language :: Python
Classifier: Programming Language :: Python :: 3
Classifier: Programming Language :: Python :: 3.10
Classifier: Topic :: Scientific/Engineering :: Bio-Informatics
Requires-Python: >=3.10
License-File: LICENSE
Requires-Dist: pandas >=1.5.3
Requires-Dist: parasail >=1.3.4
Requires-Dist: Pillow >=9.4.0
Requires-Dist: PuLP >=2.7.0
Requires-Dist: scipy >=1.11.4
Requires-Dist: snapgene-reader >=0.1.20
Requires-Dist: tqdm >=4.66.1
Requires-Dist: biopython >=1.83
Requires-Dist: Cython >=3.0.7
Requires-Dist: matplotlib >=3.7.1
Requires-Dist: numpy >=1.23.5
Requires-Dist: pyspoa >=0.2.1
